{
  "cues": [
    {
      "text": "I hear the drum echoing tonight",
      "startTime": 24.193423,
      "endTime": 27.211056
    },
    {
      "text": "But she hears only whispers of some quiet conversation",
      "startTime": 27.847994,
      "endTime": 34.147106
    },
    {
      "text": "She's coming in, 12:30 flight",
      "startTime": 36.077316,
      "endTime": 38.888909
    },
    {
      "text": "Her moonlit wings reflect the stars that guide me towards salvation",
      "startTime": 39.399092,
      "endTime": 45.872277
    },
    {
      "text": "I stopped an old man along the way",
      "startTime": 47.745669,
      "endTime": 50.66841
    },
    {
      "text": "Hoping to find some old forgotten words or ancient melodies",
      "startTime": 51.398897,
      "endTime": 57.644841
    },
    {
      "text": "He turned to me as if to say",
      "startTime": 59.446947,
      "endTime": 62.561142
    },
    {
      "text": "\"Hurry boy, it's waiting there for you\"",
      "startTime": 62.878629,
      "endTime": 67.053385
    },
    {
      "text": "It's gonna take a lot to drag me away from you",
      "startTime": 69.76368,
      "endTime": 74.663113
    },
    {
      "text": "There's nothing that a hundred men or more could ever do",
      "startTime": 75.084281,
      "endTime": 79.910382
    },
    {
      "text": "I bless the rains down in Africa",
      "startTime": 80.207848,
      "endTime": 84.941699
    },
    {
      "text": "Gonna take some time to do the things we never had",
      "startTime": 85.455245,
      "endTime": 94.242805
    },
    {
      "text": "The wild dogs cry out in the night",
      "startTime": 103.600343,
      "endTime": 106.542377
    },
    {
      "text": "As they grow restless longing for some solitary company",
      "startTime": 107.036941,
      "endTime": 113.409125
    },
    {
      "text": "I know that I must do what's right",
      "startTime": 115.425973,
      "endTime": 118.17027
    },
    {
      "text": "Sure as Kilimanjaro rises like Olympus above the Serengeti",
      "startTime": 118.357815,
      "endTime": 125.043824
    },
    {
      "text": "I seek to cure what's deep inside",
      "startTime": 127.282,
      "endTime": 130.221769
    },
    {
      "text": "Frightened of this thing that I've become",
      "startTime": 130.582886,
      "endTime": 134.642864
    },
    {
      "text": "It's gonna take a lot to drag me away from you",
      "startTime": 137.413839,
      "endTime": 142.417178
    },
    {
      "text": "There's nothing that a hundred men or more could ever do",
      "startTime": 142.936499,
      "endTime": 147.147003
    },
    {
      "text": "I bless the rains down in Africa",
      "startTime": 148.166976,
      "endTime": 152.867655
    },
    {
      "text": "Gonna take some time to do the things we never had",
      "startTime": 153.258419,
      "endTime": 161.122566
    },
    {
      "text": "\"Hurry, boy, she's waiting there for you\"",
      "startTime": 186.975942,
      "endTime": 190.775917
    },
    {
      "text": "It's gonna take a lot to drag me away from you",
      "startTime": 193.715482,
      "endTime": 198.592957
    },
    {
      "text": "There's nothing that a hundred men or more could ever do",
      "startTime": 198.949208,
      "endTime": 203.656402
    },
    {
      "text": "I bless the rains down in Africa",
      "startTime": 204.15751,
      "endTime": 208.93622
    },
    {
      "text": "I bless the rains down in Africa",
      "startTime": 209.539882,
      "endTime": 214.008224
    },
    {
      "text": "I bless the rains down in Africa",
      "startTime": 214.795601,
      "endTime": 219.470141
    },
    {
      "text": "I bless the rains down in Africa",
      "startTime": 219.984472,
      "endTime": 224.816354
    },
    {
      "text": "I bless the rains down in Africa",
      "startTime": 225.204943,
      "endTime": 229.825049
    },
    {
      "text": "Gonna take some time to do the things we never had",
      "startTime": 230.33944,
      "endTime": 238.774003
    }
  ]
}
